speak2py/__init__.py
speak2py/cli.py
speak2py/file_reader.py
speak2py/sandbox.py
speak2py/session.py
speak2py/providers/__init__.py
speak2py/providers/auto_server.py
speak2py-0.3.1.dist-info/METADATA
speak2py-0.3.1.dist-info/WHEEL
speak2py-0.3.1.dist-info/entry_points.txt
speak2py-0.3.1.dist-info/top_level.txt
speak2py-0.3.1.dist-info/RECORD
