Metadata-Version: 2.4
Name: speak2py
Version: 0.3.1
Summary: Stateful natural-language → pandas/matplotlib, offline-first.
Home-page: https://github.com/varunpuli/speak2py
Author: Varun Pulipati
Author-email: varunpulipati26@gmail.com
License: MIT
Requires-Python: >=3.10
Requires-Dist: pandas>=2.0
Requires-Dist: matplotlib>=3.6
Requires-Dist: openpyxl>=3.1
Provides-Extra: local
Dynamic: author
Dynamic: author-email
Dynamic: description
Dynamic: description-content-type
Dynamic: home-page
Dynamic: license
Dynamic: provides-extra
Dynamic: requires-dist
Dynamic: requires-python
Dynamic: summary
